{
  "kind": "singleType",
  "collectionName": "landing_pages",
  "info": {
    "singularName": "landing-page",
    "pluralName": "landing-pages",
    "displayName": "landingPage",
    "description": ""
  },
  "options": {
    "draftAndPublish": true
  },
  "pluginOptions": {},
  "attributes": {
    "logo": {
      "type": "media",
      "multiple": false,
      "required": true,
      "allowedTypes": [
        "images"
      ]
    },
    "Header": {
      "displayName": "header",
      "type": "component",
      "repeatable": false,
      "component": "basics.header"
    },
    "sectionAbout": {
      "displayName": "sectionAbout",
      "type": "component",
      "repeatable": false,
      "component": "page.section-about"
    },
    "sectionList": {
      "displayName": "sectionList",
      "type": "component",
      "repeatable": false,
      "component": "page.section-list"
    },
    "sectionConcepts": {
      "displayName": "sectionConcepts",
      "type": "component",
      "repeatable": false,
      "component": "page.section-concepts"
    },
    "listModules": {
      "displayName": "sectionModules",
      "type": "component",
      "repeatable": false,
      "component": "page.section-modules"
    }
  }
}
